sioyek/__init__.py
sioyek/add_text.py
sioyek/dual_panelify.py
sioyek/embed_annotations.py
sioyek/extract_highlights.py
sioyek/import_annotations.py
sioyek/paper_downloader.py
sioyek/remove_annotation.py
sioyek/sioyek.py
sioyek/translate.py
sioyek-0.31.10.dist-info/METADATA
sioyek-0.31.10.dist-info/WHEEL
sioyek-0.31.10.dist-info/licenses/LICENSE.txt
sioyek-0.31.10.dist-info/RECORD
