Metadata-Version: 2.1
Name: sioyek
Version: 0.31.10
Summary: Python tools and extensions for sioyek PDF reader
Project-URL: Homepage, https://github.com/ahrm/sioyek-python-extensions
Project-URL: Bug Tracker, https://github.com/ahrm/sioyek-python-extensions/issues
Author-email: Ali Mostafavi <a.hr.mostafavi@gmail.com>
License-File: LICENSE.txt
Classifier: License :: OSI Approved :: GNU General Public License v3 (GPLv3)
Classifier: Operating System :: OS Independent
Classifier: Programming Language :: Python :: 3
Requires-Python: >=3.7
Requires-Dist: appdirs>=1.4
Requires-Dist: googletrans==3.1.0a0
Requires-Dist: habanero>=1.2.2
Requires-Dist: numpy>=1.8
Requires-Dist: pymupdf>=1.2
Requires-Dist: pypaperbot>=1
Requires-Dist: pypdf2>=3
Requires-Dist: pyperclip>=1.8
Requires-Dist: pyqt5>=5.15
Requires-Dist: regex>=2.5.83
